igstt.py
igstt-0.1.1.dist-info/METADATA
igstt-0.1.1.dist-info/WHEEL
igstt-0.1.1.dist-info/entry_points.txt
igstt-0.1.1.dist-info/licenses/LICENSE
igstt-0.1.1.dist-info/RECORD
