Metadata-Version: 2.4
Name: iGSTT
Version: 0.1.1
Summary: Gemini STT CLI
License: MIT
License-File: LICENSE
Keywords: LRC,Gemini
Author: iChochy
Author-email: me@ichochy.com
Requires-Python: >=3.13
Classifier: License :: OSI Approved :: MIT License
Classifier: Programming Language :: Python :: 3
Classifier: Programming Language :: Python :: 3.13
Classifier: Programming Language :: Python :: 3.14
Requires-Dist: google-genai (>=1.36.0,<2.0.0)
Project-URL: Homepage, https://stt.ichochy.com
